{
  "users": [],
  "examples": [
    {
      "id": 1,
      "content": "Asus"
    },
    {
      "id": 2,
      "content": "Lenovo"
    },
    {
      "id": 3,
      "content": "Acer"
    },
    {
      "id": 4
    },
    {
      "id": 5
    },
    {
      "xiomay": "",
      "id": 6
    },
    {
      "sandi": "",
      "id": 7
    },
    {
      "content": "sandi",
      "id": 8
    },
    {
      "content": "bandung lautan api",
      "id": 9
    },
    {
      "content": "xiomay 1",
      "id": 10
    },
    {
      "content": "sandi 1",
      "id": 11
    },
    {
      "content": "xiomay",
      "id": 12
    },
    {
      "content": "sandi",
      "id": 13
    }
  ],
  "books": []
}